casting/apps/casting_query_bot/__init__.py
casting/apps/casting_query_bot/__main__.py
casting/apps/casting_query_bot/config.py
casting/apps/casting_query_bot/engine_bridge.py
casting/apps/casting_query_bot/tool_chat_engine.py
casting_query_bot-0.1.1.dist-info/WHEEL
casting_query_bot-0.1.1.dist-info/entry_points.txt
casting_query_bot-0.1.1.dist-info/METADATA
casting_query_bot-0.1.1.dist-info/RECORD
