Metadata-Version: 2.3
Name: casting-query-bot
Version: 0.1.1
Summary: Darcy Discord bot application
Requires-Dist: cast-query
Requires-Dist: casting-discord-framework
Requires-Dist: casting-config
Requires-Dist: llmgine
Requires-Dist: litellm
Requires-Python: >=3.13
